senior_swe_ai/__init__.py
senior_swe_ai/cache.py
senior_swe_ai/cli.py
senior_swe_ai/conf.py
senior_swe_ai/consts.py
senior_swe_ai/file_handler.py
senior_swe_ai/git_process.py
senior_swe_ai/llm_handler.py
senior_swe_ai/panel.py
senior_swe_ai/tree_parser/__init__.py
senior_swe_ai/tree_parser/base.py
senior_swe_ai/tree_parser/tree_parser_c.py
senior_swe_ai/tree_parser/tree_parser_cpp.py
senior_swe_ai/tree_parser/tree_parser_cs.py
senior_swe_ai/tree_parser/tree_parser_go.py
senior_swe_ai/tree_parser/tree_parser_java.py
senior_swe_ai/tree_parser/tree_parser_js.py
senior_swe_ai/tree_parser/tree_parser_kt.py
senior_swe_ai/tree_parser/tree_parser_py.py
senior_swe_ai/tree_parser/tree_parser_rb.py
senior_swe_ai/tree_parser/tree_parser_registry.py
senior_swe_ai/tree_parser/tree_parser_rs.py
senior_swe_ai/tree_parser/tree_parser_ts.py
senior_swe_ai/vec_store.py
senior_swe_ai-0.1.3.dist-info/METADATA
senior_swe_ai-0.1.3.dist-info/WHEEL
senior_swe_ai-0.1.3.dist-info/entry_points.txt
senior_swe_ai-0.1.3.dist-info/RECORD
